{
    "needsErrorInfo": false,
    "boxShadow": "none",
    "mobileBottomRow": 21,
    "widgetName": "InpSport",
    "displayName": "Switch",
    "iconSVG": "/static/media/icon.c0b4c50c8e9e6060b0525341b26d016d.svg",
    "searchTags": ["boolean"],
    "topRow": 19,
    "bottomRow": 23,
    "parentRowSpace": 10,
    "type": "SWITCH_WIDGET",
    "alignWidget": "LEFT",
    "hideCard": false,
    "mobileRightColumn": 27,
    "animateLoading": true,
    "parentColumnSpace": 5.99658203125,
    "dynamicTriggerPathList": [],
    "leftColumn": 14,
    "dynamicBindingPathList": [{"key": "accentColor"}],
    "labelPosition": "Left",
    "isDisabled": false,
    "key": "7b8xx71wiw",
    "isDeprecated": false,
    "rightColumn": 26,
    "thumbnailSVG": "/static/media/thumbnail.cd04c6d6a11266a806cebe39829607cb.svg",
    "dynamicHeight": "AUTO_HEIGHT",
    "widgetId": "ge3j0fs6um",
    "accentColor": "{{appsmith.theme.colors.primaryColor}}",
    "isVisible": true,
    "label": "",
    "defaultSwitchState": false,
    "version": 1,
    "parentId": "0sdqbzne9p",
    "tags": ["Toggles"],
    "renderMode": "CANVAS",
    "isLoading": false,
    "mobileTopRow": 17,
    "responsiveBehavior": "fill",
    "originalTopRow": 19,
    "mobileLeftColumn": 15,
    "maxDynamicHeight": 9000,
    "originalBottomRow": 23,
    "minDynamicHeight": 4
}